{
  "timestamp": "2025-06-28T08:38:25.957544",
  "cpu_analysis": {
    "average_cpu": 75.0,
    "peak_cpu": 90.0,
    "readings": [
      70,
      80,
      90,
      85,
      75
    ],
    "high_usage_detected": true
  },
  "augment_processes": [
    {
      "pid": 12345,
      "name": "code-insiders",
      "cpu_percent": 85.0,
      "memory_mb": 256.0
    }
  ],
  "secrets_indicators": [
    "high_disk_io"
  ],
  "augment_extensions": [],
  "recommendations": [
    "High CPU usage detected - consider Augment version rollback",
    "High disk I/O detected - check for secrets processing"
  ]
}